Metadata-Version: 2.1
Name: odoo13-addon-l10n-es-aeat
Version: 13.0.4.0.0
Summary: Modulo base para declaraciones de la AEAT
Home-page: https://github.com/OCA/l10n-spain
Author: Pexego, Acysos S.L., AvanzOSC, Tecnativa, Odoo Community Association (OCA)
Author-email: support@odoo-community.org
License: AGPL-3
Platform: UNKNOWN
Classifier: Programming Language :: Python
Classifier: Framework :: Odoo
Classifier: Framework :: Odoo :: 13.0
Classifier: License :: OSI Approved :: GNU Affero General Public License v3
Classifier: Development Status :: 6 - Mature
Requires-Python: >=3.5
Requires-Dist: odoo13-addon-account-tax-balance
Requires-Dist: odoo (<13.1dev,>=13.0a)
Requires-Dist: pyOpenSSL
Requires-Dist: unidecode
